kivy_automate-0.1.dist-info/RECORD
kivy_automate-0.1.dist-info/top_level.txt
kivy_automate-0.1.dist-info/WHEEL
kivy_automate-0.1.dist-info/METADATA
kivy_automate-0.1.dist-info/metadata.json
automate/server.py
automate/client.py
automate/install.py
automate/__init__.py
